st_attn_cuda.cpython-311-x86_64-linux-gnu.so
st_attn/__init__.py
st_attn-1.0.0.dist-info/METADATA
st_attn-1.0.0.dist-info/WHEEL
st_attn-1.0.0.dist-info/top_level.txt
st_attn-1.0.0.dist-info/RECORD
